chatterbox/__init__.py
chatterbox/chatter.py
chatterbox/memory.py
chatterbox/response.py
chatterbox/rule.py
chatterbox/utils.py
chatterbox.py-0.2.5.dist-info/METADATA
chatterbox.py-0.2.5.dist-info/RECORD
chatterbox.py-0.2.5.dist-info/WHEEL
chatterbox.py-0.2.5.dist-info/top_level.txt
